{
  "@context": "https://schema.org",
  "generated_at": "2026-07-06T06:50:53.628Z",
  "base_url": "https://www.bliainara.co.il",
  "currency": "ILS",
  "count": 25,
  "products": [
    {
      "id": "b02fc454-c917-4abf-882a-36dc5d2776cb",
      "slug": "tsmyd-tbat-prchym-vbvddym-mshvbtsym-zyrkvnym-mntsntsym-mpldt-al-chld-btsypvy-zhb-aykvty-ittgu5",
      "name": "צמיד טבעת פרחים ובודדים משובצים זירקונים מנצנצים מפלדת אל חלד בציפוי זהב איכותי",
      "name_translations": {
        "en": "Flower Ring Bracelet with Sparkling Zirconia Inlays in Quality Gold-Plated Stainless Steel",
        "he": "צמיד טבעת פרחים ובודדים משובצים זירקונים מנצנצים מפלדת אל חלד בציפוי זהב איכותי"
      },
      "description": "<p>סטייל ואופנה ביד לכל רגע</p>",
      "short_description": "צמיד טבעת פרחים ובודדים משובצים זירקונים מנצנצים בציפוי זהב איכותי על פלדת אל חלד",
      "sku": "304226303001007012g",
      "brand": "בלי עין הרע",
      "price": 119,
      "base_price": 159,
      "sale_price": 119,
      "currency": "ILS",
      "images": [
        "https://www.bliainara.co.il/assets/product-1783273208612-m59sk9j.webp",
        "https://www.bliainara.co.il/assets/product-enhanced-1783273666227-uo2d59.webp"
      ],
      "in_stock": true,
      "stock_status": "in_stock",
      "url": "https://www.bliainara.co.il/product/tsmyd-tbat-prchym-vbvddym-mshvbtsym-zyrkvnym-mntsntsym-mpldt-al-chld-btsypvy-zhb-aykvty-ittgu5",
      "categories": [
        "בלי עין הרע לנשים"
      ],
      "updated_at": "2026-07-05T17:51:17.414Z"
    },
    {
      "id": "fdac2dad-6f23-456d-abe8-7a56109e9078",
      "slug": "tsmyd-tbat-mavynym-mshvbtsym-zyrkvnym-mntsntsym-mpldt-al-chld-btsypvy-zhb-aykvty-qy3ds9",
      "name": "צמיד טבעת מעוינים משובצים זירקונים מנצנצים מפלדת אל חלד בציפוי זהב איכותי",
      "name_translations": {
        "en": "Diamond-Shaped Ring Bracelet with Sparkling Zirconia Stones in Quality Gold-Plated Stainless Steel",
        "he": "צמיד טבעת מעוינים משובצים זירקונים מנצנצים מפלדת אל חלד בציפוי זהב איכותי"
      },
      "description": "<p>סטייל ואופנה ביד בכל רגע</p>",
      "short_description": "צמיד טבעת מעוינים משובצים זירקונים מפלדת אל חלד בציפוי זהב איכותי, מתאים ליום יום ולארועים",
      "sku": "304226303001007012g",
      "brand": "בלי עין הרע",
      "price": 119,
      "base_price": 159,
      "sale_price": 119,
      "currency": "ILS",
      "images": [
        "https://www.bliainara.co.il/assets/product-1783272155273-x63l9l.webp",
        "https://www.bliainara.co.il/assets/product-ai-fit-1783272497422-e0a2nl.webp"
      ],
      "in_stock": true,
      "stock_status": "in_stock",
      "url": "https://www.bliainara.co.il/product/tsmyd-tbat-mavynym-mshvbtsym-zyrkvnym-mntsntsym-mpldt-al-chld-btsypvy-zhb-aykvty-qy3ds9",
      "categories": [
        "בלי עין הרע לנשים"
      ],
      "updated_at": "2026-07-05T17:34:36.596Z"
    },
    {
      "id": "0be8bc0a-5ed1-4396-9d50-5e36d5266e80",
      "slug": "tsmyd-tbat-mavynym-mshvbtsym-zyrkvnym-mntsntsym-mpldt-al-chld-ksvpym-4zla27",
      "name": "צמיד טבעת מעוינים משובצים זירקונים מנצנצים מפלדת אל חלד כסופים ",
      "name_translations": {
        "en": "Diamond-Shaped Bangle Bracelet with Sparkling Zirconia Stones in Silver Stainless Steel ",
        "he": "צמיד טבעת מעוינים משובצים זירקונים מנצנצים מפלדת אל חלד כסופים "
      },
      "description": "<p>צמיד טבעת מהמם ומנצנץ סטייל ואופנה על היד בכל רגע</p>",
      "short_description": "צמיד טבעת מהמם ומנצנץ מפלדת אל חלד, מתאים גם ליום יום וגם לארועים",
      "sku": "304226303001007012s",
      "brand": "בלי עין הרע",
      "price": 109,
      "base_price": 149,
      "sale_price": 109,
      "currency": "ILS",
      "images": [
        "https://www.bliainara.co.il/assets/product-1783270829516-yk3cje.webp",
        "https://www.bliainara.co.il/assets/product-enhanced-1783270909437-y9iy.webp"
      ],
      "in_stock": true,
      "stock_status": "in_stock",
      "url": "https://www.bliainara.co.il/product/tsmyd-tbat-mavynym-mshvbtsym-zyrkvnym-mntsntsym-mpldt-al-chld-ksvpym-4zla27",
      "categories": [
        "בלי עין הרע לנשים"
      ],
      "updated_at": "2026-07-05T17:07:29.825Z"
    },
    {
      "id": "d2a342ca-796e-4b62-a7a1-efe15fd7109f",
      "slug": "shrshrt-tlyvn-agvl-ayn-hra-mpldt-al-chld-btsypvy-zhb-aykvty-lshmyrh-vhgnh-mayn-hra-gxe9jj",
      "name": "שרשרת תליון עגול עין הרע מפלדת אל חלד בציפוי זהב איכותי לשמירה והגנה מעין הרע",
      "name_translations": {
        "en": "Round Evil Eye Pendant Necklace in Gold-Plated Stainless Steel for Protection Against the Evil Eye",
        "he": "שרשרת תליון עגול עין הרע מפלדת אל חלד בציפוי זהב איכותי לשמירה והגנה מעין הרע"
      },
      "description": "<p>שרשרת תליון עדינה נגד עין הרע להגנה ושמירה מתאימה ליום יום ולארועים</p>",
      "short_description": "שרשרת תליון עין הרע מפלדת אל חלד בציפוי זהב איכותי, תליון עגול כחול נגד עין הרע, קוטר התליון:1ס\"מ, אורך השרשרת:40+5ס\"מ",
      "sku": "302785198501005060g",
      "brand": "בלי עין הרע",
      "price": 119,
      "base_price": 159,
      "sale_price": 119,
      "currency": "ILS",
      "images": [
        "https://www.bliainara.co.il/assets/product-1783241899977-591yy6.webp",
        "https://www.bliainara.co.il/assets/product-enhanced-1783241994561-djccd.webp"
      ],
      "in_stock": true,
      "stock_status": "in_stock",
      "url": "https://www.bliainara.co.il/product/shrshrt-tlyvn-agvl-ayn-hra-mpldt-al-chld-btsypvy-zhb-aykvty-lshmyrh-vhgnh-mayn-hra-gxe9jj",
      "categories": [
        "בלי עין הרע לנשים"
      ],
      "updated_at": "2026-07-05T09:44:39.215Z"
    },
    {
      "id": "1b72c6a7-da60-463a-a99c-26e75b4ad3fb",
      "slug": "shrshrt-tlyvn-ayn-hra-agvlh-kchvlh-mpldt-al-chld-ksvph-lshmyrh-vhgnh-mayn-hra-xg7y9r",
      "name": "שרשרת תליון עין הרע עגולה כחולה מפלדת אל חלד כסופה לשמירה והגנה מעין הרע",
      "name_translations": {
        "en": "Silver Stainless Steel Round Blue Evil Eye Pendant Necklace for Protection and Warding Off the Evil Eye",
        "he": "שרשרת תליון עין הרע עגולה כחולה מפלדת אל חלד כסופה לשמירה והגנה מעין הרע"
      },
      "description": "<p>להגנה ושמירה נגד עין הרע לסטייל יומיומי וגם לארועים</p>",
      "short_description": "שרשרת תליון עדינה,עגולה ,עין כחולה מפלדת אל חלד,קוטר תליון:1ס\"מ, אורך שרשרת:40+5ס\"מ",
      "sku": "302785198501005060s",
      "brand": "בלי עין הרע",
      "price": 109,
      "base_price": 149,
      "sale_price": 109,
      "currency": "ILS",
      "images": [
        "https://www.bliainara.co.il/assets/product-1783241077164-u5ni9o.webp",
        "https://www.bliainara.co.il/assets/product-enhanced-1783241253868-429wdb.webp"
      ],
      "in_stock": true,
      "stock_status": "in_stock",
      "url": "https://www.bliainara.co.il/product/shrshrt-tlyvn-ayn-hra-agvlh-kchvlh-mpldt-al-chld-ksvph-lshmyrh-vhgnh-mayn-hra-xg7y9r",
      "categories": [
        "בלי עין הרע לנשים"
      ],
      "updated_at": "2026-07-05T08:51:09.661Z"
    },
    {
      "id": "3ac36390-0147-4bba-85d5-c9d530e9223f",
      "slug": "shrshrt-lgbr-babvdt-yd-mklypvt-kvkvs-tbayym-chrvzy-ats-vabnym-tbayvt-btsba-kchvl-khh-o5fgep",
      "name": "שרשרת לגבר בעבודת יד מקליפות קוקוס טבעיים חרוזי עץ ואבנים טבעיות בצבע כחול כהה",
      "name_translations": {
        "en": "Handmade Men's Necklace with Natural Coconut Shells, Wood Beads and Natural Stones in Dark Blue",
        "he": "שרשרת לגבר בעבודת יד מקליפות קוקוס טבעיים חרוזי עץ ואבנים טבעיות בצבע כחול כהה"
      },
      "description": "<p>שרשרת בעבודת יד לאוהבי הסטייל הטבעי ליום יום</p>",
      "short_description": "שרשרת לגבר בעבודת יד משולבת קליפות קוקוס, חרוזי עץ ואבן טבעית כחולה כהה, אורך שרשרת:45+5ס\"מ, עובי שרשרת:0.6ס\"מ, סגר שרשרת מצופה זהב איכותי",
      "sku": "302785198501005060n",
      "brand": "בלי עין הרע",
      "price": 109,
      "base_price": 149,
      "sale_price": 109,
      "currency": "ILS",
      "images": [
        "https://www.bliainara.co.il/assets/product-1783238830997-3u7d0o.webp",
        "https://www.bliainara.co.il/assets/product-enhanced-1783238874511-ygz6gn.webp"
      ],
      "in_stock": true,
      "stock_status": "in_stock",
      "url": "https://www.bliainara.co.il/product/shrshrt-lgbr-babvdt-yd-mklypvt-kvkvs-tbayym-chrvzy-ats-vabnym-tbayvt-btsba-kchvl-khh-o5fgep",
      "categories": [
        "בלי עין הרע לגברים"
      ],
      "updated_at": "2026-07-05T08:12:19.336Z"
    },
    {
      "id": "8de052c2-ada7-4f03-bcc7-c1c908aef8ec",
      "slug": "shrshrt-lgbr-abvdt-yd-mklypvt-kvkvs-tbayym-chrvzy-ats-vabnym-tbayvt-btsba-kchvl-mnth-siq82c",
      "name": "שרשרת לגבר עבודת יד מקליפות קוקוס טבעיים חרוזי עץ ואבנים טבעיות בצבע כחול מנטה",
      "name_translations": {
        "en": "Handmade Men's Necklace with Natural Coconut Shells, Wood Beads and Natural Stones in Mint Blue",
        "he": "שרשרת לגבר עבודת יד מקליפות קוקוס טבעיים חרוזי עץ ואבנים טבעיות בצבע כחול מנטה"
      },
      "description": "<p>לאוהבי סטייל טבעי ליום יום</p>",
      "short_description": "שרשרת עבודת יד טבעית אורך:45+5ס\"מ, עובי שרשרת:0.6ס\"מ, סגר השרשרת מצופים זהב איכותי",
      "sku": "302785198501005060n",
      "brand": "בלי עין הרע",
      "price": 109,
      "base_price": 149,
      "sale_price": 109,
      "currency": "ILS",
      "images": [
        "https://www.bliainara.co.il/assets/product-1783237248144-bzqzb.webp",
        "https://www.bliainara.co.il/assets/product-enhanced-1783237320996-csc9s.webp"
      ],
      "in_stock": true,
      "stock_status": "in_stock",
      "url": "https://www.bliainara.co.il/product/shrshrt-lgbr-abvdt-yd-mklypvt-kvkvs-tbayym-chrvzy-ats-vabnym-tbayvt-btsba-kchvl-mnth-siq82c",
      "categories": [
        "בלי עין הרע לגברים"
      ],
      "updated_at": "2026-07-05T07:42:43.801Z"
    },
    {
      "id": "b5396540-c913-4e9c-be37-43802069ea38",
      "slug": "shrshrt-lgbr-mklypvt-kvkvs-tbayym-bshylvb-chrvzy-ats-vabnym-tbayvt-btsba-yrvk-mnth-5pg10z",
      "name": "שרשרת לגבר מקליפות קוקוס טבעיים בשילוב חרוזי עץ ואבנים טבעיות בצבע ירוק מנטה",
      "name_translations": {
        "en": "Men's Necklace Made from Natural Coconut Shells Combined with Wood Beads and Natural Stones in Mint Green",
        "he": "שרשרת לגבר מקליפות קוקוס טבעיים בשילוב חרוזי עץ ואבנים טבעיות בצבע ירוק מנטה"
      },
      "description": "<p>שרשרת בעבודת יד לגבר בשילוב חומרים טבעיים לאוהבי הסטייל הטבעי והאופנה הטבעית ליום יום</p>",
      "short_description": "שרשרת מדהימה לגבר בעבודת יד בשילוב קליפות קוקוס, חרוזי עץ ואבן טבעית ירוקה מנטה, סגר ושרשרת בציפוי זהב איכותי \nאורך שרשרת: 45+5 ס\"מ, עובי שרשרת:0.6ס\"מ",
      "sku": "302785198501005060n",
      "brand": "בלי עין הרע",
      "price": 109,
      "base_price": 149,
      "sale_price": 109,
      "currency": "ILS",
      "images": [
        "https://www.bliainara.co.il/assets/product-1783234059008-wmdbb9.webp",
        "https://www.bliainara.co.il/assets/product-enhanced-1783234633850-y1etgp.webp"
      ],
      "in_stock": true,
      "stock_status": "in_stock",
      "url": "https://www.bliainara.co.il/product/shrshrt-lgbr-mklypvt-kvkvs-tbayym-bshylvb-chrvzy-ats-vabnym-tbayvt-btsba-yrvk-mnth-5pg10z",
      "categories": [
        "בלי עין הרע לגברים"
      ],
      "updated_at": "2026-07-05T06:57:40.528Z"
    },
    {
      "id": "97373e0c-6c85-472d-a5e9-d62e0d869c8c",
      "slug": "shrshrt-tlyvn-mavdnym-mpt-yshral-bshylvb-mgn-dvyd-adyn-mpldt-al-chld-btsypvy-zhb-aykvty-9595bs",
      "name": "שרשרת תליון מעודנים ,מפת ישראל בשילוב מגן דויד עדין מפלדת אל חלד בציפוי זהב איכותי",
      "name_translations": {
        "en": "Elegant Pendant Necklace, Map of Israel Combined with a Delicate Star of David in Quality Gold-Plated Stainless Steel",
        "he": "שרשרת תליון מעודנים ,מפת ישראל בשילוב מגן דויד עדין מפלדת אל חלד בציפוי זהב איכותי"
      },
      "description": "<p>שרשרת תליון מעודנים, מפת ארץ ישראל בשילוב מגן דויד בציפוי זהב, מתאים לסטייל יום יומי ולארועים</p>",
      "short_description": "שרשרת תליון מעודנים מפת ישראל בשילוב מגן דויד מפלדת אל חלד בציפוי זהב איכותי, אורך תליון:3.5ס\"מ, רוחב תליון:1ס\"מ ,אורך שרשרת:כ-46 ס\"מ",
      "sku": "302785198501005060g",
      "brand": "בלי עין הרע",
      "price": 119,
      "base_price": 159,
      "sale_price": 119,
      "currency": "ILS",
      "images": [
        "https://www.bliainara.co.il/assets/product-1783231993924-39pgug.webp",
        "https://www.bliainara.co.il/assets/product-enhanced-1783232186562-88375k.webp"
      ],
      "in_stock": true,
      "stock_status": "in_stock",
      "url": "https://www.bliainara.co.il/product/shrshrt-tlyvn-mavdnym-mpt-yshral-bshylvb-mgn-dvyd-adyn-mpldt-al-chld-btsypvy-zhb-aykvty-9595bs",
      "categories": [
        "בלי עין הרע לנשים"
      ],
      "updated_at": "2026-07-05T06:38:51.801Z"
    },
    {
      "id": "33a48049-20b9-4924-ae85-619184910682",
      "slug": "shrshrt-tlyvn-ksvpym-mpt-yshral-mshvlbt-mgn-dvyd-adyn-mpldt-al-chld-tkf01h",
      "name": "שרשרת תליון כסופים, מפת ישראל משולבת מגן דויד עדין מפלדת אל חלד",
      "name_translations": {
        "en": "Silver Pendant Necklace, Israel Map Combined with Delicate Star of David, Stainless Steel",
        "he": "שרשרת תליון כסופים, מפת ישראל משולבת מגן דויד עדין מפלדת אל חלד"
      },
      "description": "<p>שרשרת תליון מעודנים מפלדת אל חלד כסופים ליום יום וגם לארועים</p>",
      "short_description": "שרשרת תליון מפת ישראל מעודנת מפלדת אל חלד, אורך תליון:3.5ס\"מ, רוחב תליון:1ס\"מ, אורך שרשרת:כ-46 ס\"מ",
      "sku": "302785198501005060s",
      "brand": "בלי עין הרע",
      "price": 109,
      "base_price": 149,
      "sale_price": 109,
      "currency": "ILS",
      "images": [
        "https://www.bliainara.co.il/assets/product-1783230940688-zn3t3.webp",
        "https://www.bliainara.co.il/assets/product-enhanced-1783231357753-ox7d1.webp"
      ],
      "in_stock": true,
      "stock_status": "in_stock",
      "url": "https://www.bliainara.co.il/product/shrshrt-tlyvn-ksvpym-mpt-yshral-mshvlbt-mgn-dvyd-adyn-mpldt-al-chld-tkf01h",
      "categories": [
        "בלי עין הרע לנשים"
      ],
      "updated_at": "2026-07-05T06:41:50.216Z"
    },
    {
      "id": "a0fc5a81-a842-4e30-88f1-aa53ec352d9c",
      "slug": "shrshrt-tlyvn-chy-mpldt-al-chld-mtsvpym-zhb-aykvty-lbrkharykvt-ymymshpa-vhgnh-szhxc6",
      "name": "שרשרת תליון חי מפלדת אל חלד מצופים זהב איכותי לברכה,אריכות ימים,שפע והגנה",
      "name_translations": {
        "en": "Chai Pendant Necklace in Gold-Plated Stainless Steel for Blessing, Longevity, Abundance and Protection",
        "he": "שרשרת תליון חי מפלדת אל חלד מצופים זהב איכותי לברכה,אריכות ימים,שפע והגנה"
      },
      "description": "<p>לברכה, הצלחה, שפע והגנה עוצמתיים מהקבלה</p>",
      "short_description": "שרשרת תליון חי מפלדת אל חלד מצופים זהב איכותי, רוחב תליון:1.7ס\"מ, אורך תליון:1.6ס\"מ, אורך שרשרת: 45+5ס\"מ\nבשילוב אותיות קבלה עוצמתיות לשפע, ברכה, הגנה.\nמתאים ללוק וסטייל אופנתי יום יומי ולארועים",
      "sku": "298188219501008033gg",
      "brand": "בלי עין הרע",
      "price": 119,
      "base_price": 159,
      "sale_price": 119,
      "currency": "ILS",
      "images": [
        "https://www.bliainara.co.il/assets/product-1783191675392-lx2bh7.webp",
        "https://www.bliainara.co.il/assets/product-enhanced-1783191774335-hwf6f.webp"
      ],
      "in_stock": true,
      "stock_status": "in_stock",
      "url": "https://www.bliainara.co.il/product/shrshrt-tlyvn-chy-mpldt-al-chld-mtsvpym-zhb-aykvty-lbrkharykvt-ymymshpa-vhgnh-szhxc6",
      "categories": [
        "בלי עין הרע לגברים"
      ],
      "updated_at": "2026-07-04T19:03:45.345Z"
    },
    {
      "id": "908378ca-6b0b-4651-8646-0e1c1fcda0b1",
      "slug": "shrshrt-tlyvn-chy-mpldt-al-chld-ksvpym-lbrkharykvt-ymymshpa-vhgnh-hhxww0",
      "name": "שרשרת תליון חי מפלדת אל חלד כסופים לברכה,אריכות ימים,שפע והגנה",
      "name_translations": {
        "en": "Silver Stainless Steel Chai Pendant Necklace for Blessing, Longevity, Abundance and Protection",
        "he": "שרשרת תליון חי מפלדת אל חלד כסופים לברכה,אריכות ימים,שפע והגנה"
      },
      "description": "<p>שרשרת תליון חי בשילוב אותיות אלוהים בקבלה, סגולה עוצמתית בשילוב לוק סטייליסטי ואופנתי ליום יום וגם לארועים</p>",
      "short_description": "שרשרת תליון חי בשילוב אותיות י,ו,מ אשר מסמלים את שם אלוהים בקבלה, רצף זה נחשב לסגולה רבת עוצמה לשמירה,הצלחה ולהגנה מעין הרע. רוחב תליון:1.7ס\"מ, אורך תליון:1.6 ס\"מ, אורך שרשרת: 45+5 ס\"מ",
      "sku": "298188219501008033s",
      "brand": "בלי עין הרע",
      "price": 109,
      "base_price": 149,
      "sale_price": 109,
      "currency": "ILS",
      "images": [
        "https://www.bliainara.co.il/assets/product-1783190738578-n1ptom.webp",
        "https://www.bliainara.co.il/assets/product-enhanced-1783190849389-spjq1.webp"
      ],
      "in_stock": true,
      "stock_status": "in_stock",
      "url": "https://www.bliainara.co.il/product/shrshrt-tlyvn-chy-mpldt-al-chld-ksvpym-lbrkharykvt-ymymshpa-vhgnh-hhxww0",
      "categories": [
        "בלי עין הרע לגברים"
      ],
      "updated_at": "2026-07-04T18:49:01.101Z"
    },
    {
      "id": "659ee31e-e297-4486-9b25-5ebfac83b88e",
      "slug": "shrshrt-tlyvn-agvl-shma-yshral-mpldt-al-chld-mtsvpym-zhb-aykvty-lbrkhshmyrh-vhgnh-8ob4yg",
      "name": "שרשרת תליון עגול שמע ישראל מפלדת אל חלד מצופים זהב איכותי לברכה,שמירה והגנה",
      "name_translations": {
        "en": "Round Shema Israel Pendant Necklace in Gold-Plated Stainless Steel for Blessing, Protection and Guardianship",
        "he": "שרשרת תליון עגול שמע ישראל מפלדת אל חלד מצופים זהב איכותי לברכה,שמירה והגנה"
      },
      "description": "<p>שרשרת תליון מהממת שמע ישראל עגול מפלדת אל חלד מצופה זהב איכותי לברכה,שמירה והגנה ללוק סטיליסטי ואופנתי ליום יום ולארועים</p>",
      "short_description": "שרשרת תליון מהממים, תליון עגול קוטר:2.8ס\"מ, מפלדת אל חלד מצופים זהב איכותי, אורך השרשרת 60 ס\"מ.  לברכה, שמירה, הגנה ולוק סטיליסטי ואופנתי ליום יום וגם לארועים",
      "sku": null,
      "brand": "בלי עין הרע",
      "price": 119,
      "base_price": 159,
      "sale_price": 119,
      "currency": "ILS",
      "images": [
        "https://www.bliainara.co.il/assets/product-1783188025755-nwt81l.webp",
        "https://www.bliainara.co.il/assets/product-enhanced-1783189434835-q14ggh.webp"
      ],
      "in_stock": true,
      "stock_status": "in_stock",
      "url": "https://www.bliainara.co.il/product/shrshrt-tlyvn-agvl-shma-yshral-mpldt-al-chld-mtsvpym-zhb-aykvty-lbrkhshmyrh-vhgnh-8ob4yg",
      "categories": [
        "בלי עין הרע לגברים"
      ],
      "updated_at": "2026-07-04T18:26:48.656Z"
    },
    {
      "id": "6bc392da-f6e3-4af7-b9d1-a37db1df07bc",
      "slug": "shrshrt-tlyvn-agvl-shma-yshral-mpldt-al-chld-ksvpym-lbrkh-shmyrh-vhgnh-dlqd5l",
      "name": "שרשרת תליון עגול שמע ישראל מפלדת אל חלד כסופים לברכה, שמירה והגנה",
      "name_translations": {
        "en": "Round Shema Israel Pendant Necklace in Silver Stainless Steel for Blessing, Protection and Guardianship",
        "he": "שרשרת תליון עגול שמע ישראל מפלדת אל חלד כסופים לברכה, שמירה והגנה"
      },
      "description": "<p>שרשרת תליון מדהים סטיליסטי ואופנתי עם ברכת שמע ישראל לברכה, שמירה והגנה, מתאים ליום יום ולארועים</p>",
      "short_description": "שרשרת תליון עגול סטייליסטי ואופנתי שמע ישראל מפלדת אל חלד כסוף, קוטר תליון:2.8 ס\"מ, אורך שרשרת:60 ס\"מ",
      "sku": "298188219501008033s",
      "brand": "בלי עין הרע",
      "price": 109,
      "base_price": 149,
      "sale_price": 109,
      "currency": "ILS",
      "images": [
        "https://www.bliainara.co.il/assets/product-1783186315352-a1327q.webp"
      ],
      "in_stock": true,
      "stock_status": "in_stock",
      "url": "https://www.bliainara.co.il/product/shrshrt-tlyvn-agvl-shma-yshral-mpldt-al-chld-ksvpym-lbrkh-shmyrh-vhgnh-dlqd5l",
      "categories": [
        "בלי עין הרע לגברים"
      ],
      "updated_at": "2026-07-04T17:48:32.254Z"
    },
    {
      "id": "d9091540-6cc7-4240-9d11-adf2c731b9af",
      "slug": "shrshrt-tlyvn-mgn-dvyd-mpldt-al-chld-btsypvy-zhb-aykvty-rvchb26sm-avrk-29sm-g8gd94",
      "name": "שרשרת תליון מגן דויד מפלדת אל חלד בציפוי זהב איכותי, רוחב:2.6ס\"מ, אורך: 2.9ס\"מ",
      "name_translations": {
        "en": "Star of David Pendant Necklace in Gold-Plated Stainless Steel, Width: 2.6cm, Length: 2.9cm",
        "he": "שרשרת תליון מגן דויד מפלדת אל חלד בציפוי זהב איכותי, רוחב:2.6ס\"מ, אורך: 2.9ס\"מ"
      },
      "description": "<p>שרשרת תליון מגן דויד עשוי מפלדת אל חלד מצופים זהב איכותי, ללוק וסטייל יומיומי ולארועים</p>",
      "short_description": "שרשרת תליון מגן דויד מפלדת אל חלד מצופים זהב איכותי, אורך שרשרת: 45-50ס\"מ",
      "sku": "298188219501008033g",
      "brand": "בלי עין הרע",
      "price": 119,
      "base_price": 159,
      "sale_price": 119,
      "currency": "ILS",
      "images": [
        "https://www.bliainara.co.il/assets/product-1783181161806-7ajm1z.webp",
        "https://www.bliainara.co.il/assets/product-1783181709923-6trsbv.webp"
      ],
      "in_stock": true,
      "stock_status": "in_stock",
      "url": "https://www.bliainara.co.il/product/shrshrt-tlyvn-mgn-dvyd-mpldt-al-chld-btsypvy-zhb-aykvty-rvchb26sm-avrk-29sm-g8gd94",
      "categories": [
        "בלי עין הרע לגברים"
      ],
      "updated_at": "2026-07-04T16:51:04.219Z"
    },
    {
      "id": "b377d917-705e-448a-b306-e311d69a3bd1",
      "slug": "shrshrt-tlyvn-mgn-dvyd-mpldt-al-chld-ksvp-gdvl-rvchb26sm-gvbh29sm-904sal",
      "name": "שרשרת תליון מגן דויד מפלדת אל חלד כסוף גדול, רוחב:2.6ס\"מ, גובה:2.9ס\"מ",
      "name_translations": {
        "en": "Large Silver Stainless Steel Star of David Pendant Necklace, Width: 2.6cm, Height: 2.9cm",
        "he": "שרשרת תליון מגן דויד מפלדת אל חלד כסוף גדול, רוחב:2.6ס\"מ, גובה:2.9ס\"מ"
      },
      "description": "<p>שרשרת תליון מגן דויד כסוף מפלדת אל חלד ללוק סטייל יומיומי</p>",
      "short_description": "שרשרת תליון מגן דויד מפלדת אל חלד כסוף גדול, אורך שרשרת:45-50 ס\"מ",
      "sku": "298188219501008033s",
      "brand": "בלי עין הרע",
      "price": 109,
      "base_price": 149,
      "sale_price": 109,
      "currency": "ILS",
      "images": [
        "https://www.bliainara.co.il/assets/product-1783180113883-1k2x3c.webp",
        "https://www.bliainara.co.il/assets/product-enhanced-1783180169776-zulznt.webp"
      ],
      "in_stock": true,
      "stock_status": "in_stock",
      "url": "https://www.bliainara.co.il/product/shrshrt-tlyvn-mgn-dvyd-mpldt-al-chld-ksvp-gdvl-rvchb26sm-gvbh29sm-904sal",
      "categories": [
        "בלי עין הרע לגברים"
      ],
      "updated_at": "2026-07-04T15:56:55.411Z"
    },
    {
      "id": "d45f1546-1da8-4158-b66a-22260d660a8c",
      "slug": "shrshrt-tlyvn-brkt-hkhnym-mpldt-al-chld-btsypvy-zhb-aykvty-v8sbz3",
      "name": "שרשרת תליון ברכת הכהנים מפלדת אל חלד בציפוי זהב איכותי",
      "name_translations": {
        "en": "Priestly Blessing Pendant Necklace in Stainless Steel with Quality Gold Plating",
        "he": "שרשרת תליון ברכת הכהנים מפלדת אל חלד בציפוי זהב איכותי"
      },
      "description": "<p>שרשרת תליון ברכת הכהנים לברכה, שמירה והגנה בתוספת סטייל ללוק שלך ליום יום ולארועים</p>",
      "short_description": "שרשרת תליון לברכה והגנה ברכת הכהנים, עשויים מפלדת אל חלד וציפוי זהב איכותי, אורך תליון:3.9 ס\"מ, עובי ורוחב:0.5 ס\"מ, אורך שרשרת: 45-50ס\"מ",
      "sku": "298188219501008033g",
      "brand": "בלי עין הרע",
      "price": 119,
      "base_price": 159,
      "sale_price": 119,
      "currency": "ILS",
      "images": [
        "https://www.bliainara.co.il/assets/product-1783178612265-6s5w2g.webp",
        "https://www.bliainara.co.il/assets/product-enhanced-1783178855565-s3u4dp.webp"
      ],
      "in_stock": true,
      "stock_status": "in_stock",
      "url": "https://www.bliainara.co.il/product/shrshrt-tlyvn-brkt-hkhnym-mpldt-al-chld-btsypvy-zhb-aykvty-v8sbz3",
      "categories": [
        "בלי עין הרע לגברים"
      ],
      "updated_at": "2026-07-04T15:28:33.589Z"
    },
    {
      "id": "f27cee67-b28b-4665-8cab-3017901d26d0",
      "slug": "shrshrt-tlyvn-brkt-hkhnym-mpldt-al-chld-ieg84k",
      "name": "שרשרת תליון ברכת הכהנים מפלדת אל חלד ",
      "name_translations": {
        "en": "Priestly Blessing Pendant Necklace in Stainless Steel",
        "he": "שרשרת תליון ברכת הכהנים מפלדת אל חלד "
      },
      "description": "<p>שרשרת תליון מפלדת אל חלד איכותית, ברכת הכהנים לשמירה והגנה בנוסף ללוק ולסטייל שלך</p>",
      "short_description": "שרשרת ותליון ברכת הכהנים מפלדת אל חלד, אורך:3.9 ס\"מ, עובי ורוחב:0.5 ס\"מ\nשרשרת אורך: 45-50 ס\"מ",
      "sku": "29818821950100833",
      "brand": "בלי עין הרע",
      "price": 109,
      "base_price": 149,
      "sale_price": 109,
      "currency": "ILS",
      "images": [
        "https://www.bliainara.co.il/assets/product-1782974525329-45qqdi.webp",
        "https://www.bliainara.co.il/assets/product-enhanced-1783064058854-4jcivf.webp"
      ],
      "in_stock": true,
      "stock_status": "in_stock",
      "url": "https://www.bliainara.co.il/product/shrshrt-tlyvn-brkt-hkhnym-mpldt-al-chld-ieg84k",
      "categories": [
        "בלי עין הרע לגברים"
      ],
      "updated_at": "2026-07-04T15:10:41.635Z"
    },
    {
      "id": "271d1140-af01-4c89-9612-3ee98ff86ee5",
      "slug": "shrshrt-am-tlyvn-mgn-dvyd-agvl-adyn-mtsvpym-zhb-aykvty-mshvbts-babny-zyrkvn-msbyb-z9g2sn",
      "name": "שרשרת עם תליון מגן דויד עגול עדין מצופים זהב איכותי משובץ באבני זירקון מסביב",
      "name_translations": {
        "en": "שרשרת עם תליון מגן דויד עגול עדין מצופים זהב איכותי משובץ באבני זירקון מסביב",
        "he": "שרשרת עם תליון מגן דויד עגול עדין מצופים זהב איכותי משובץ באבני זירקון מסביב"
      },
      "description": "<p>שרשרת עם תליון מגן דויד מפלדת אל חלד מצופים בזהב איכותי בשיבוץ זירקונים מסביב, קוטר 2.1 ס\"מ מתאים גם ליום יום וגם לארועים מנצנצים</p>",
      "short_description": "שרשרת עם תליון מגן דויד מפלדת אל חלד, עגול, עדין, מצופים זהב איכותי, תליון משובץ באבני זירקון, קוטר 2.1 ס\"מ",
      "sku": "298188219501008033go",
      "brand": "בלי עין הרע",
      "price": 119,
      "base_price": 159,
      "sale_price": 119,
      "currency": "ILS",
      "images": [
        "https://www.bliainara.co.il/assets/product-1782921511438-l4o66a.webp",
        "https://www.bliainara.co.il/assets/product-enhanced-1782921838052-t3pgxh.webp"
      ],
      "in_stock": true,
      "stock_status": "in_stock",
      "url": "https://www.bliainara.co.il/product/shrshrt-am-tlyvn-mgn-dvyd-agvl-adyn-mtsvpym-zhb-aykvty-mshvbts-babny-zyrkvn-msbyb-z9g2sn",
      "categories": [
        "בלי עין הרע לנשים"
      ],
      "updated_at": "2026-07-01T16:35:01.304Z"
    },
    {
      "id": "6e26cc75-df17-4eeb-b733-0f1610227dd3",
      "slug": "shrshrt-am-tlyvn-mgn-dvyd-agvl-adyn-mshvbts-babny-zyrkvn-msbyb-vy2lgf",
      "name": "שרשרת עם תליון מגן דויד עגול עדין משובץ באבני זירקון מסביב",
      "name_translations": {
        "en": "שרשרת עם תליון מגן דויד עגול עדין משובץ באבני זירקון מסביב",
        "he": "שרשרת עם תליון מגן דויד עגול עדין משובץ באבני זירקון מסביב"
      },
      "description": "<p>תליון מגן דויד עדין ומהמם המתאים ליום יום וגם לארועים בזכות השיבוץ בזירקונים מנצנצים</p>",
      "short_description": "מיוצר מפלדת אל חלד ,קוטר תליון 2.1 ס\"מ משובץ אבני זירקון",
      "sku": "29818821950108033sil",
      "brand": "בלי עין הרע",
      "price": 109,
      "base_price": 149,
      "sale_price": 109,
      "currency": "ILS",
      "images": [
        "https://www.bliainara.co.il/assets/product-1782919798499-w41wro.webp",
        "https://www.bliainara.co.il/assets/product-enhanced-1782919964107-cfxnab.webp"
      ],
      "in_stock": true,
      "stock_status": "in_stock",
      "url": "https://www.bliainara.co.il/product/shrshrt-am-tlyvn-mgn-dvyd-agvl-adyn-mshvbts-babny-zyrkvn-msbyb-vy2lgf",
      "categories": [
        "בלי עין הרע לנשים"
      ],
      "updated_at": "2026-07-01T16:35:01.318Z"
    },
    {
      "id": "46f0110b-d3d7-41b2-9125-4663ebf53d33",
      "slug": "tsmyd-mhmm-chvm-klva-babvdt-yd-bshylvb-abny-ayn-hnmr-hmyvchdvt-2myzgd",
      "name": "צמיד מהמם חום קלוע בעבודת יד בשילוב אבני עין הנמר המיוחדות",
      "name_translations": {
        "en": "צמיד מהמם חום קלוע בעבודת יד בשילוב אבני עין הנמר המיוחדות",
        "he": "צמיד מהמם חום קלוע בעבודת יד בשילוב אבני עין הנמר המיוחדות"
      },
      "description": "<p>צמיד מהמם לגבר חום קלוע בעבודת יד בשילוב אבני עין הנמר, סגירה בטוחה מפלדת אל חלד, קוטר כ-21 ס\"מ</p><p>תוספת מרשימה ללוק שלך...</p>",
      "short_description": "צמיד מהמם חום קלוע בעבודת יד בשילוב אבני עין הנמר המיוחדות והאנרגטיות, תוספת מרשימה ללוק שלך...\nאבזם לסגירה בטוחה שחור מפלדת אל חלד, קוטר כ-21 ס\"מ",
      "sku": "3021409310010120060br",
      "brand": "בלי עין הרע",
      "price": 109,
      "base_price": 139,
      "sale_price": 109,
      "currency": "ILS",
      "images": [
        "https://www.bliainara.co.il/assets/product-1782715276242-bls5je.webp",
        "https://www.bliainara.co.il/assets/product-ai-fit-1782715357698-i2vfy.webp"
      ],
      "in_stock": true,
      "stock_status": "in_stock",
      "url": "https://www.bliainara.co.il/product/tsmyd-mhmm-chvm-klva-babvdt-yd-bshylvb-abny-ayn-hnmr-hmyvchdvt-2myzgd",
      "categories": [
        "בלי עין הרע לגברים"
      ],
      "updated_at": "2026-07-01T16:35:01.322Z"
    },
    {
      "id": "71aa7027-9c85-4807-8cbc-a9045c7596b5",
      "slug": "tsmyd-mhmm-lbn-klva-babvdt-yd-bshylvb-abny-ayn-hnmr-hmyvchdvt-rbkiem",
      "name": "צמיד מהמם לבן קלוע בעבודת יד בשילוב אבני עין הנמר המיוחדות",
      "name_translations": {
        "en": "צמיד מהמם לבן קלוע בעבודת יד בשילוב אבני עין הנמר המיוחדות",
        "he": "צמיד מהמם לבן קלוע בעבודת יד בשילוב אבני עין הנמר המיוחדות"
      },
      "description": "<p>צמיד מהמם לבן בעבודת יד קלוע בשילוב אבני עין הנמר המיוחדות והאנרגטיות שלא נותנות להתעלם ומוסיפות ללוק המיוחד שלך...</p><p>אבזם שחור לסגירה בטוחה מפלדת אל חלד, קוטר כ-21 ס\"מ</p>",
      "short_description": "צמיד מהמם ומיוחד לבן קלוע בעבודת יד בשילוב אבני עין הנמר המיוחדות, אבזם סגירה בטוחה מפלדת אל חלד שחור, קוטר כ-21 ס\"מ",
      "sku": "3021409310010120060w",
      "brand": "בלי עין הרע",
      "price": 109,
      "base_price": 139,
      "sale_price": 109,
      "currency": "ILS",
      "images": [
        "https://www.bliainara.co.il/assets/product-1782658701275-by6e4i.webp",
        "https://www.bliainara.co.il/assets/product-1782658870429-voes3l.webp"
      ],
      "in_stock": true,
      "stock_status": "in_stock",
      "url": "https://www.bliainara.co.il/product/tsmyd-mhmm-lbn-klva-babvdt-yd-bshylvb-abny-ayn-hnmr-hmyvchdvt-rbkiem",
      "categories": [
        "בלי עין הרע לגברים"
      ],
      "updated_at": "2026-07-01T16:35:01.328Z"
    },
    {
      "id": "cdbe64f2-5681-4ee0-9e3e-5469bb42a290",
      "slug": "tsmyd-mhmm-shchvr-klva-babvdt-yd-bshylvb-abny-ayn-hnmr-hmyvchdvt-lxvzsm",
      "name": "צמיד מהמם שחור קלוע בעבודת יד בשילוב אבני עין הנמר המיוחדות",
      "name_translations": {
        "en": "צמיד מהמם שחור קלוע בעבודת יד בשילוב אבני עין הנמר המיוחדות",
        "he": "צמיד מהמם שחור קלוע בעבודת יד בשילוב אבני עין הנמר המיוחדות"
      },
      "description": "<p>צמיד מהמם ומיוחד שחור קלוע בשילוב אבני עין הנמר המיוחדות, אבזם שחור מפלדת אל חלד לסגירה בטוחה, קוטר כ-21 ס\"מ, תוספת מרשימה ללוק שלך...</p>",
      "short_description": "צמיד שחור קלוע בעבודת יד משולב אבני עין הנמר, אבזם שחור לסגירה מגנטית בטוחה מפלדת אל חלד שחור, קוטר כ-21 ס\"מ\nתוספת מהממת ללוק שלך...",
      "sku": "3021409310010120060b",
      "brand": "בלי עין הרע",
      "price": 109,
      "base_price": 139,
      "sale_price": 109,
      "currency": "ILS",
      "images": [
        "https://www.bliainara.co.il/assets/product-1782656299161-zcfd9k.webp",
        "https://www.bliainara.co.il/assets/product-1782656361634-0bbv49.webp"
      ],
      "in_stock": true,
      "stock_status": "in_stock",
      "url": "https://www.bliainara.co.il/product/tsmyd-mhmm-shchvr-klva-babvdt-yd-bshylvb-abny-ayn-hnmr-hmyvchdvt-lxvzsm",
      "categories": [
        "בלי עין הרע לגברים"
      ],
      "updated_at": "2026-07-01T16:35:01.359Z"
    },
    {
      "id": "8252a47c-daef-4ae6-97b5-206faf63cca0",
      "slug": "tsmyd-chvm-mshvlb-klva-aykvty-babvdt-yd-lgbrsgyrh-mgntyt-mpldt-al-chld-btvchh-qmnly7",
      "name": "צמיד חום משולב קלוע איכותי בעבודת יד לגבר,סגירה מגנטית מפלדת אל חלד בטוחה",
      "name_translations": {
        "en": "צמיד חום משולב קלוע איכותי בעבודת יד לגבר,סגירה מגנטית מפלדת אל חלד בטוחה",
        "he": "צמיד חום משולב קלוע איכותי בעבודת יד לגבר,סגירה מגנטית מפלדת אל חלד בטוחה"
      },
      "description": "<p>צמיד חום אופנתי משולב קלוע בעבודת יד לגבר, סגירה ופתיחה בטוחה ,סגר מפלדת אל חלד שחור, קוטר כ-21 ס\"מ</p>",
      "short_description": "צמיד חום אופנתי משולב קלוע בעבודת יד לגבר, סגירה מגנטית מפלדת אל חלד בטוחה, קוטר כ-21 ס\"מ",
      "sku": "3028878260007068br",
      "brand": "בלי עין הרע",
      "price": 69,
      "base_price": 79,
      "sale_price": 69,
      "currency": "ILS",
      "images": [
        "https://www.bliainara.co.il/assets/product-1782652602429-78vqk.webp",
        "https://www.bliainara.co.il/assets/product-ai-fit-1782653604002-zs7efk.webp"
      ],
      "in_stock": true,
      "stock_status": "in_stock",
      "url": "https://www.bliainara.co.il/product/tsmyd-chvm-mshvlb-klva-aykvty-babvdt-yd-lgbrsgyrh-mgntyt-mpldt-al-chld-btvchh-qmnly7",
      "categories": [
        "בלי עין הרע לגברים"
      ],
      "updated_at": "2026-07-01T16:35:01.375Z"
    },
    {
      "id": "1d66e94b-33f5-4d84-8700-51bfa1b0acf5",
      "slug": "tsmyd-shchvr-mshvlb-klva-aykvty-babvdt-yd-lgbr-sgyrh-mgntyt-mpldt-al-chld-btvchh-copy-zazrem",
      "name": "צמיד שחור משולב קלוע איכותי בעבודת יד לגבר סגירה מגנטית מפלדת אל חלד בטוחה (Copy)",
      "name_translations": {
        "en": "צמיד שחור משולב קלוע איכותי בעבודת יד לגבר סגירה מגנטית מפלדת אל חלד בטוחה (Copy)",
        "he": "צמיד שחור משולב קלוע איכותי בעבודת יד לגבר סגירה מגנטית מפלדת אל חלד בטוחה (Copy)"
      },
      "description": "<p>צמיד שחור משולב קלוע ואיכותי בעבודת יד, סגירת מגנט אבזם שחור פלדת אל חלד איכותי לגבר, קוטר כ-21 ס\"מ</p>",
      "short_description": "צמיד יד שחור משולב קלוע איכותי לגבר בעבודת יד, סגירה מגנטית בטוחה מפלדת אל חלד, קוטר כ-21 ס\"מ",
      "sku": "30288782600-07068b",
      "brand": "בלי עין הרע",
      "price": 69,
      "base_price": 79,
      "sale_price": 69,
      "currency": "ILS",
      "images": [
        "https://www.bliainara.co.il/assets/product-1782458570544-2dn6j.webp",
        "https://www.bliainara.co.il/assets/product-ai-fit-1782458820042-4tldv9.webp"
      ],
      "in_stock": true,
      "stock_status": "in_stock",
      "url": "https://www.bliainara.co.il/product/tsmyd-shchvr-mshvlb-klva-aykvty-babvdt-yd-lgbr-sgyrh-mgntyt-mpldt-al-chld-btvchh-copy-zazrem",
      "categories": [
        "בלי עין הרע לגברים"
      ],
      "updated_at": "2026-07-01T16:35:01.373Z"
    }
  ]
}